{
  "generado": "2026-07-01T13:52:20",
  "default": "2026-06",
  "periodos": [
    {
      "periodo": "2026-06",
      "mes_nombre": "Junio",
      "anio": "2026",
      "dias": 26,
      "primer_dia": "2026-06-01",
      "ultimo_dia": "2026-06-30",
      "generado": "2026-07-01T13:52:20",
      "total_gestores": 77,
      "total_gestiones": 403453,
      "total_efectivas": 58213,
      "total_promesas": 26046,
      "total_recaudo": 2328305.08,
      "tasa_contacto": 0.1443,
      "ptp_rate": 0.4474,
      "con_metas": true
    },
    {
      "periodo": "2026-05",
      "mes_nombre": "Mayo",
      "anio": "2026",
      "dias": 24,
      "primer_dia": "2026-05-02",
      "ultimo_dia": "2026-05-30",
      "generado": "2026-07-01T13:51:14",
      "total_gestores": 66,
      "total_gestiones": 290988,
      "total_efectivas": 51239,
      "total_promesas": 23317,
      "total_recaudo": 1634830.73,
      "tasa_contacto": 0.1761,
      "ptp_rate": 0.4551,
      "con_metas": false
    },
    {
      "periodo": "2026-04",
      "mes_nombre": "Abril",
      "anio": "2026",
      "dias": 24,
      "primer_dia": "2026-04-01",
      "ultimo_dia": "2026-04-30",
      "generado": "2026-07-01T13:50:29",
      "total_gestores": 63,
      "total_gestiones": 360260,
      "total_efectivas": 47450,
      "total_promesas": 22349,
      "total_recaudo": 1528786.42,
      "tasa_contacto": 0.1317,
      "ptp_rate": 0.471,
      "con_metas": false
    },
    {
      "periodo": "2026-03",
      "mes_nombre": "Marzo",
      "anio": "2026",
      "dias": 26,
      "primer_dia": "2026-03-02",
      "ultimo_dia": "2026-03-31",
      "generado": "2026-07-01T13:49:32",
      "total_gestores": 62,
      "total_gestiones": 326528,
      "total_efectivas": 52388,
      "total_promesas": 25759,
      "total_recaudo": 1532170.3,
      "tasa_contacto": 0.1604,
      "ptp_rate": 0.4917,
      "con_metas": false
    },
    {
      "periodo": "2026-02",
      "mes_nombre": "Febrero",
      "anio": "2026",
      "dias": 21,
      "primer_dia": "2026-02-02",
      "ultimo_dia": "2026-02-28",
      "generado": "2026-07-01T13:48:33",
      "total_gestores": 62,
      "total_gestiones": 315575,
      "total_efectivas": 47205,
      "total_promesas": 22156,
      "total_recaudo": 1232070.64,
      "tasa_contacto": 0.1496,
      "ptp_rate": 0.4694,
      "con_metas": false
    }
  ]
}